MANIFEST.in
README.md
main.py
setup.py
FKanban.egg-info/PKG-INFO
FKanban.egg-info/SOURCES.txt
FKanban.egg-info/dependency_links.txt
FKanban.egg-info/requires.txt
FKanban.egg-info/top_level.txt
Fkanban/Fkanban.py
Fkanban/__init__.py
Fkanban/item.py
Fkanban/kanban.py
Fkanban/kloop.py
Fkanban/nomenclature.py
Fkanban/operation.py
Fkanban/place.py
Fkanban/ui_Fkanban.py
Fkanban/ui_object.py
Fkanban/ui_stat.py
Fkanban/workshop.py
example/config.py